cayaml/__init__.py
cayaml/api.py
cayaml/ast_nodes.py
cayaml/parser.py
cayaml/plain_conversion.py
cayaml/unparser.py
cayaml-0.1.1.dist-info/METADATA
cayaml-0.1.1.dist-info/WHEEL
cayaml-0.1.1.dist-info/RECORD
